camphr_core/VERSION.py
camphr_core/__init__.py
camphr_core/consts.py
camphr_core/errors.py
camphr_core/lang/__init__.py
camphr_core/lang/juman/__init__.py
camphr_core/lang/juman/tag_map.py
camphr_core/lang/mecab/__init__.py
camphr_core/lang/mecab/tag_map.py
camphr_core/lang/sentencepiece/__init__.py
camphr_core/lang/stop_words.py
camphr_core/ner_labels/Makefile
camphr_core/ner_labels/__init__.py
camphr_core/ner_labels/ene.yml
camphr_core/ner_labels/labels_ene.py
camphr_core/ner_labels/labels_irex.py
camphr_core/ner_labels/labels_ontonotes.py
camphr_core/ner_labels/labels_wikipedia.py
camphr_core/ner_labels/ontonotes.yml
camphr_core/ner_labels/package.json
camphr_core/ner_labels/sekine.yml
camphr_core/ner_labels/utils.py
camphr_core/ner_labels/wikipedia.yml
camphr_core/py.typed
camphr_core/types.py
camphr_core/utils.py
camphr_core-0.1.0.dist-info/entry_points.txt
camphr_core-0.1.0.dist-info/WHEEL
camphr_core-0.1.0.dist-info/METADATA
camphr_core-0.1.0.dist-info/RECORD
